data_to_model/__init__.py
data_to_model/console/__init__.py
data_to_model/console/application.py
data_to_model/data_parsers/__init__.py
data_to_model/data_parsers/csv_parser.py
data_to_model/data_parsers/data_parser.py
data_to_model/data_parsers/factory.py
data_to_model/data_parsers/types.py
data_to_model/generators/__init__.py
data_to_model/generators/base_generator.py
data_to_model/generators/dataclass_generator.py
data_to_model/generators/factory.py
data_to_model/generators/types.py
data_to_model/model_generator.py
data_to_model/models/__init__.py
data_to_model/models/class_data.py
data_to_model/models/class_field.py
data_to_model/models/data_class_model.py
data_to_model/name_formatters/__init__.py
data_to_model/name_formatters/camel_case_formatter.py
data_to_model/name_formatters/name_formatter.py
data_to_model/name_formatters/snake_case_formatter.py
data_to_model/type_detectors/__init__.py
data_to_model/type_detectors/type_detector.py
data_to_model/type_detectors/types.py
data2model-0.2.1b0.dist-info/entry_points.txt
data2model-0.2.1b0.dist-info/LICENSE
data2model-0.2.1b0.dist-info/WHEEL
data2model-0.2.1b0.dist-info/METADATA
data2model-0.2.1b0.dist-info/RECORD
