Metadata-Version: 2.1
Name: data2model
Version: 0.2.1b0
Summary: Python library and CLI tool for converting data to different Python data classes
Home-page: https://github.com/dmitriiweb/data2model
License: MIT
Keywords: code,generator,cli,tools
Author: Dmitrii Kurlov
Author-email: dmitriik@protonmail.com
Requires-Python: >=3.8,<3.11
Classifier: Development Status :: 4 - Beta
Classifier: License :: OSI Approved :: MIT License
Classifier: Operating System :: MacOS
Classifier: Operating System :: Microsoft :: Windows
Classifier: Operating System :: Unix
Classifier: Programming Language :: Python :: 3
Classifier: Programming Language :: Python :: 3.10
Classifier: Programming Language :: Python :: 3.8
Classifier: Programming Language :: Python :: 3.9
Classifier: Programming Language :: Python :: Implementation :: CPython
Classifier: Topic :: Utilities
Requires-Dist: aiocsv (>=1.2.1,<2.0.0)
Requires-Dist: aiofiles (>=0.8.0,<0.9.0)
Requires-Dist: anyio (>=3.5.0,<4.0.0)
Requires-Dist: click (>=8.0.3,<9.0.0)
